{
    "label": "AY.20",
    "description": "AY.20 defining mutations - acquired along the path to the root of the lineage and remain conserved within the lineage",
    "sources": [],
    "type": "lineage",
    "tags": [
        "AY.20"
    ],
    "sites": [
        "nuc:G210T",
        "nuc:C241T",
        "orf1a:A599V",
        "nuc:C3037T",
        "orf1a:A1306S",
        "orf1a:P2046L",
        "orf1a:P2287S",
        "nuc:C8986T",
        "orf1a:V2930L",
        "orf1a:T3255I",
        "orf1a:T3646A",
        "nuc:A11332G",
        "orf1b:P314L",
        "orf1b:G662S",
        "orf1b:P1000L",
        "orf1b:A1918V",
        "s:T19R",
        "s:L452R",
        "s:T478K",
        "s:D614G",
        "s:P681R",
        "s:D950N",
        "s:V1104L",
        "orf3a:S26L",
        "m:I82T",
        "orf7a:V82A",
        "orf7a:T120I",
        "nuc:C27874T",
        "n:R203M",
        "n:G215C",
        "n:D377Y",
        "nuc:G29742T",
        "nuc:T8782C",
        "orf8:L84S"
    ],
    "rules": {
        "min_alt": "26",
        "max_ref": "5",
        "orf1a:A599V": "alt"
    },
    "intermediate": [
        "s:T95I:97.9975480179812",
        "n:D63G:99.59133633020024"
    ]
}